adafruit_lps2x.py
adafruit_circuitpython_lps2x-3.0.13.dist-info/licenses/LICENSE
adafruit_circuitpython_lps2x-3.0.13.dist-info/METADATA
adafruit_circuitpython_lps2x-3.0.13.dist-info/WHEEL
adafruit_circuitpython_lps2x-3.0.13.dist-info/top_level.txt
adafruit_circuitpython_lps2x-3.0.13.dist-info/RECORD
